porphyry/__init__.py
porphyry/porphyry.py
porphyry-0.0.1.dist-info/LICENSE
porphyry-0.0.1.dist-info/METADATA
porphyry-0.0.1.dist-info/WHEEL
porphyry-0.0.1.dist-info/top_level.txt
porphyry-0.0.1.dist-info/RECORD
