Metadata-Version: 2.1
Name: porphyry
Version: 0.0.1
Summary: Prediction of the current gas flow rate
Home-page: https://github.com/gubkinbot/porphyry
Author: Ivan Samorukov
Author-email: ivan@samorukov.uz
License: UNKNOWN
Project-URL: Bug Tracker, https://github.com/gubkinbot/porphyry/issues
Platform: UNKNOWN
Classifier: Programming Language :: Python :: 3
Classifier: License :: OSI Approved :: MIT License
Classifier: Operating System :: OS Independent
Requires-Python: >=3.6
License-File: LICENSE
